{"cameraMode":{"drawMode":0,"name":"Shaded","section":"Shading Mode"},"sceneLighting":true,"audioPlay":false,"sceneViewState":{"showFog":true,"showMaterialUpdate":false,"showSkybox":true,"showFlares":true,"showImageEffects":true,"showParticleSystems":true},"in2DMode":false,"pivot":{"x":68.3459701538086,"y":3.194469451904297,"z":424.5059509277344},"rotation":{"x":-0.13955675065517426,"y":0.8081293106079102,"z":-0.21222154796123506,"w":-0.5314255356788635},"size":14.790101051330567,"orthographic":false}